{
	"description": "项目配置文件",
	"packOptions": {
		"ignore": []
	},
	"setting": {
		"urlCheck": true,
		"es6": true,
		"postcss": true,
		"minified": true,
		"newFeature": true,
		"autoAudits": false
	},
	"compileType": "miniprogram",
	"libVersion": "2.4.3",
	"appid": "wx50207f901b432945",
	"projectname": "box19-%E9%9B%A8%E8%9D%B6%E6%8E%92%E5%BA%8F%E5%90%A7",
	"debugOptions": {
		"hidedInDevtools": []
	},
	"isGameTourist": false,
	"condition": {
		"search": {
			"current": -1,
			"list": []
		},
		"conversation": {
			"current": -1,
			"list": []
		},
		"plugin": {
			"current": -1,
			"list": []
		},
		"game": {
			"currentL": -1,
			"list": []
		},
		"miniprogram": {
			"current": 1,
			"list": [
				{
					"id": -1,
					"name": "liuliang",
					"pathName": "liuliang/index/index",
					"query": ""
				},
				{
					"id": -1,
					"name": "qiliang",
					"pathName": "liuliang/qiliang/qiliang"
				}
			]
		}
	}
}